keyrock_telemetry/__init__.py
keyrock_telemetry/telemetry/__init__.py
keyrock_telemetry/telemetry/logging.py
keyrock_telemetry/telemetry/postgres.py
keyrock_telemetry/telemetry/snowflake.py
keyrock_telemetry/telemetry/telemetry.py
keyrock_telemetry/telemetry/test_telemetry.py
keyrock_telemetry-2024.2.15.1117.dist-info/METADATA
keyrock_telemetry-2024.2.15.1117.dist-info/WHEEL
keyrock_telemetry-2024.2.15.1117.dist-info/top_level.txt
keyrock_telemetry-2024.2.15.1117.dist-info/RECORD
